SLiCAP/SLiCAP.py
SLiCAP/SLiCAPconfigure.py
SLiCAP/SLiCAPdesignData.py
SLiCAP/SLiCAPexecute.py
SLiCAP/SLiCAPgschem.py
SLiCAP/SLiCAPhtml.py
SLiCAP/SLiCAPinstruction.py
SLiCAP/SLiCAPkicad.py
SLiCAP/SLiCAPlatex.py
SLiCAP/SLiCAPlex.py
SLiCAP/SLiCAPltspice.py
SLiCAP/SLiCAPmath.py
SLiCAP/SLiCAPmatrices.py
SLiCAP/SLiCAPngspice.py
SLiCAP/SLiCAPplots.py
SLiCAP/SLiCAPprotos.py
SLiCAP/SLiCAPrst.py
SLiCAP/SLiCAPshell.py
SLiCAP/SLiCAPsvgTools.py
SLiCAP/SLiCAPyacc.py
SLiCAP/__init__.py
SLiCAP/docs/doctrees/environment.pickle
SLiCAP/docs/doctrees/index.doctree
SLiCAP/docs/doctrees/introduction/SLiCAPcontributions.doctree
SLiCAP/docs/doctrees/introduction/SLiCAPhow.doctree
SLiCAP/docs/doctrees/introduction/SLiCAPintroduction.doctree
SLiCAP/docs/doctrees/introduction/SLiCAPreleaseNotes.doctree
SLiCAP/docs/doctrees/introduction/SLiCAPwhy.doctree
SLiCAP/docs/doctrees/reference/SLiCAP.doctree
SLiCAP/docs/doctrees/reference/SLiCAPconfigure.doctree
SLiCAP/docs/doctrees/reference/SLiCAPdesignData.doctree
SLiCAP/docs/doctrees/reference/SLiCAPhtml.doctree
SLiCAP/docs/doctrees/reference/SLiCAPinstruction.doctree
SLiCAP/docs/doctrees/reference/SLiCAPkicad.doctree
SLiCAP/docs/doctrees/reference/SLiCAPlatex.doctree
SLiCAP/docs/doctrees/reference/SLiCAPmath.doctree
SLiCAP/docs/doctrees/reference/SLiCAPngspice.doctree
SLiCAP/docs/doctrees/reference/SLiCAPplots.doctree
SLiCAP/docs/doctrees/reference/SLiCAPprotos.doctree
SLiCAP/docs/doctrees/reference/SLiCAPreference.doctree
SLiCAP/docs/doctrees/reference/SLiCAPrst.doctree
SLiCAP/docs/doctrees/reference/SLiCAPshell.doctree
SLiCAP/docs/doctrees/syntax/SLiCAPnetlistSyntax.doctree
SLiCAP/docs/doctrees/syntax/devices.doctree
SLiCAP/docs/doctrees/syntax/netlist.doctree
SLiCAP/docs/doctrees/tutorials/SLiCAPtutorials.doctree
SLiCAP/docs/doctrees/userguide/SLiCAPuserguide.doctree
SLiCAP/docs/doctrees/userguide/analysis.doctree
SLiCAP/docs/doctrees/userguide/balanced.doctree
SLiCAP/docs/doctrees/userguide/circuit.doctree
slicap-4.0.10.dist-info/licenses/LICENCE.txt
slicap-4.0.10.dist-info/METADATA
slicap-4.0.10.dist-info/WHEEL
slicap-4.0.10.dist-info/top_level.txt
slicap-4.0.10.dist-info/RECORD
