Metadata-Version: 2.4
Name: SLiCAP
Version: 4.0.10
Summary: SLiCAP: more than SYMBOLIC SPICE
Author-email: Anton Montagne <anton@montagne.nl>
License: MIT
Project-URL: Homepage, https://slicap.github.io/SLiCAP_python/
Project-URL: Issues, https://github.com/SLiCAP/SLiCAP_python
Classifier: Programming Language :: Python :: 3
Classifier: Operating System :: OS Independent
Requires-Python: >=3.12
License-File: LICENCE.txt
Requires-Dist: numpy>=1.26
Requires-Dist: sympy>=1.12
Requires-Dist: scipy>=1.12
Requires-Dist: ply>=3.11
Requires-Dist: matplotlib>=3.8.0
Requires-Dist: svgelements>=1.9.6
Requires-Dist: svglib>=1.5.1
Requires-Dist: pytexit>=0.4.0
Requires-Dist: IPython>=8.19
Requires-Dist: windows_tools>=2.4; sys_platform == "win32"
Requires-Dist: pywin32>306; sys_platform == "win32"
Requires-Dist: docutils>=0.18
Requires-Dist: sphinx-rtd-theme>=1.2.0
Dynamic: license-file
